gsodpy/__init__.py
gsodpy/gsodpy.py
gsodpy/gsoDownloader/__init__.py
gsodpy/gsoDownloader/gsoDownloader.py
gsodpy-0.0.1.dist-info/LICENSE
gsodpy-0.0.1.dist-info/METADATA
gsodpy-0.0.1.dist-info/WHEEL
gsodpy-0.0.1.dist-info/top_level.txt
gsodpy-0.0.1.dist-info/RECORD
