Metadata-Version: 2.1
Name: gsodpy
Version: 0.0.1
Summary: A basic package for downloading and processing GSOD data
Home-page: https://github.com/wino6687/gsodpy
Author: Will Norris
Author-email: willnorris303@gmail.com
License: UNKNOWN
Platform: UNKNOWN
Classifier: Programming Language :: Python :: 3
Classifier: License :: OSI Approved :: MIT License
Classifier: Operating System :: OS Independent
